roadwarrior.py
setup.py
roadwarrior.egg-info/PKG-INFO
roadwarrior.egg-info/SOURCES.txt
roadwarrior.egg-info/dependency_links.txt
roadwarrior.egg-info/entry_points.txt
roadwarrior.egg-info/top_level.txt