Metadata-Version: 1.0
Name: roadwarrior
Version: 0.0.2
Summary: Tool for working remotely on large code bases.
Home-page: https://github.com/denniskempin/roadwarrior
Author: Dennis Kempin
Author-email: dennis.kempin@gmail.com
License: MIT
Platform: UNKNOWN
